<?xml version="1.0" encoding="utf-8"?>
<ConstantsHolder xmlns:xsi="http://www.w3.org/2001/XMLSchema-instance" xmlns:xsd="http://www.w3.org/2001/XMLSchema">
  <LifeMax>20</LifeMax>
  <PheromonesNoFood>0</PheromonesNoFood>
  <PheromonesFood>3</PheromonesFood>
  <CarryMax>10</CarryMax>
  <Vision>20</Vision>
  <EatingRadius>15</EatingRadius>
  <Starvation>20</Starvation>
  <PheroFusionRadius>10</PheroFusionRadius>
  <PheroEvaporationRate>0.999</PheroEvaporationRate>
  <LarvaSpawnCooldown>180</LarvaSpawnCooldown>
  <BirthMinFood>500</BirthMinFood>
  <LarvaCost>50</LarvaCost>
  <_GlobalInertia>1.1</_GlobalInertia>
  <ScoutRandom>100</ScoutRandom>
  <ScoutGoal>-2</ScoutGoal>
  <ScoutPheromones>1</ScoutPheromones>
  <GoFoodRandom>100</GoFoodRandom>
  <GoFoodGoal>50</GoFoodGoal>
  <GoFoodPheromones>1</GoFoodPheromones>
  <BringFoodRandom>100</BringFoodRandom>
  <BringFoodGoal>50</BringFoodGoal>
  <BringFoodPheromones>1</BringFoodPheromones>
</ConstantsHolder>